x17_hash.cp36-win_amd64.pyd
x17_hash-1.6.dist-info/METADATA
x17_hash-1.6.dist-info/RECORD
x17_hash-1.6.dist-info/WHEEL
x17_hash-1.6.dist-info/top_level.txt
