Metadata-Version: 2.1
Name: x17-hash
Version: 1.6
Summary: Python X17 hash extension
Home-page: UNKNOWN
Author: cryptolgin
Author-email: c0re@tutanota.com
License: UNKNOWN
Platform: UNKNOWN
